pymsis-0.11.0.dist-info/RECORD
pymsis-0.11.0.dist-info/LICENSE
pymsis-0.11.0.dist-info/WHEEL
pymsis-0.11.0.dist-info/METADATA
pymsis/msis00f.cpython-312-darwin.so
pymsis/__init__.py
pymsis/msis.py
pymsis/utils.py
pymsis/msis20f.cpython-312-darwin.so
pymsis/msis21.parm
pymsis/msis21f.cpython-312-darwin.so
pymsis/msis2.0.parm
pymsis/tests/test_utils.py
pymsis/tests/conftest.py
pymsis/tests/msis2.1_test_ref_dp.txt
pymsis/tests/msis2.0_test_ref_dp.txt
pymsis/tests/f107_ap_test_data.txt
pymsis/tests/__init__.py
pymsis/tests/test_msis.py
pymsis/tests/test_regression.py
pymsis/.dylibs/libgfortran.5.dylib
pymsis/.dylibs/libquadmath.0.dylib
pymsis/.dylibs/libgcc_s.1.1.dylib
