Metadata-Version: 2.1
Name: pymsis
Version: 0.11.0
Summary: A Python wrapper around the NRLMSIS model.
Author-Email: Greg Lucas <greg.lucas@lasp.colorado.edu>
License: MIT License
Classifier: Development Status :: 4 - Beta
Classifier: Intended Audience :: Developers
Classifier: License :: OSI Approved :: MIT License
Classifier: Natural Language :: English
Classifier: Programming Language :: Python :: 3
Classifier: Programming Language :: Python :: 3.10
Classifier: Programming Language :: Python :: 3.11
Classifier: Programming Language :: Python :: 3.12
Classifier: Programming Language :: Python :: 3.13
Classifier: Topic :: Software Development
Classifier: Topic :: Scientific/Engineering
Classifier: Operating System :: Microsoft :: Windows
Classifier: Operating System :: POSIX
Classifier: Operating System :: Unix
Classifier: Operating System :: MacOS
Project-URL: homepage, https://swxtrec.github.io/pymsis/
Project-URL: repository, https://github.com/swxtrec/pymsis
Requires-Python: >=3.10
Requires-Dist: numpy>=1.23
Provides-Extra: test
Requires-Dist: pytest; extra == "test"
Requires-Dist: pytest-cov; extra == "test"
Provides-Extra: doc
Requires-Dist: matplotlib; extra == "doc"
Requires-Dist: myst-parser; extra == "doc"
Requires-Dist: sphinx; extra == "doc"
Requires-Dist: sphinx_gallery; extra == "doc"
Requires-Dist: pydata-sphinx-theme; extra == "doc"
Provides-Extra: dev
Requires-Dist: pymsis[doc,test]; extra == "dev"
Requires-Dist: mypy; extra == "dev"
Requires-Dist: pre-commit; extra == "dev"
Requires-Dist: ruff; extra == "dev"
